{
    "crime": "2069. Ljava/lang/StringBuilder;append->Ljava/lang/String;format",
    "permission": [],
    "api": [
        {
            "class": "Ljava/lang/StringBuilder;",
            "method": "append",
            "descriptor": "(Ljava/lang/Object;)Ljava/lang/StringBuilder;"
        },
        {
            "class": "Ljava/lang/String;",
            "method": "format",
            "descriptor": "(Ljava/lang/String; [Ljava/lang/Object;)Ljava/lang/String;"
        }
    ],
    "score": 1,
    "label": []
}