{
    "crime": "4326. Ljava/io/RandomAccessFile;<init>->Ljava/lang/IllegalStateException;<init>",
    "permission": [],
    "api": [
        {
            "class": "Ljava/io/RandomAccessFile;",
            "method": "<init>",
            "descriptor": "(Ljava/io/File; Ljava/lang/String;)V"
        },
        {
            "class": "Ljava/lang/IllegalStateException;",
            "method": "<init>",
            "descriptor": "(Ljava/lang/String;)V"
        }
    ],
    "score": 1,
    "label": []
}