{
    "crime": "4630. Ljava/util/concurrent/ConcurrentHashMap;containsKey->Ljava/util/concurrent/ConcurrentHashMap;putIfAbsent",
    "permission": [],
    "api": [
        {
            "class": "Ljava/util/concurrent/ConcurrentHashMap;",
            "method": "containsKey",
            "descriptor": "(Ljava/lang/Object;)Z"
        },
        {
            "class": "Ljava/util/concurrent/ConcurrentHashMap;",
            "method": "putIfAbsent",
            "descriptor": "(Ljava/lang/Object; Ljava/lang/Object;)Ljava/lang/Object;"
        }
    ],
    "score": 1
}