{
    "crime": "5799. Ljava/util/logging/Logger;log->Ljava/util/Arrays;asList",
    "permission": [],
    "api": [
        {
            "class": "Ljava/util/logging/Logger;",
            "method": "log",
            "descriptor": "(Ljava/util/logging/Level; Ljava/lang/String; Ljava/lang/Throwable;)V"
        },
        {
            "class": "Ljava/util/Arrays;",
            "method": "asList",
            "descriptor": "([Ljava/lang/Object;)Ljava/util/List;"
        }
    ],
    "score": 1,
    "label": []
}