{
    "crime": "7193. Ljavax/net/ssl/HttpsURLConnection;setSSLSocketFactory->Ljava/util/Iterator;hasNext",
    "permission": [],
    "api": [
        {
            "class": "Ljavax/net/ssl/HttpsURLConnection;",
            "method": "setSSLSocketFactory",
            "descriptor": "(Ljavax/net/ssl/SSLSocketFactory;)V"
        },
        {
            "class": "Ljava/util/Iterator;",
            "method": "hasNext",
            "descriptor": "()Z"
        }
    ],
    "score": 1,
    "label": []
}