{
    "crime": "8007. Ljavax/net/ssl/SSLSocketFactory;createSocket->Ljava/lang/NullPointerException;<init>",
    "permission": [],
    "api": [
        {
            "class": "Ljavax/net/ssl/SSLSocketFactory;",
            "method": "createSocket",
            "descriptor": "(Ljava/net/Socket; Ljava/lang/String; I Z)Ljava/net/Socket;"
        },
        {
            "class": "Ljava/lang/NullPointerException;",
            "method": "<init>",
            "descriptor": "(Ljava/lang/String;)V"
        }
    ],
    "score": 1,
    "label": []
}