{
    "crime": "8759. Ljava/security/cert/X509Certificate;getSubjectAlternativeNames->Ljavax/net/ssl/SSLPeerUnverifiedException;<init>",
    "permission": [],
    "api": [
        {
            "class": "Ljava/security/cert/X509Certificate;",
            "method": "getSubjectAlternativeNames",
            "descriptor": "()Ljava/util/Collection;"
        },
        {
            "class": "Ljavax/net/ssl/SSLPeerUnverifiedException;",
            "method": "<init>",
            "descriptor": "(Ljava/lang/String;)V"
        }
    ],
    "score": 1,
    "label": []
}