{
    "crime": "9695. Ljava/lang/String;format->Ljava/util/concurrent/CountDownLatch;countDown",
    "permission": [],
    "api": [
        {
            "class": "Ljava/lang/String;",
            "method": "format",
            "descriptor": "(Ljava/util/Locale; Ljava/lang/String; [Ljava/lang/Object;)Ljava/lang/String;"
        },
        {
            "class": "Ljava/util/concurrent/CountDownLatch;",
            "method": "countDown",
            "descriptor": "()V"
        }
    ],
    "score": 1,
    "label": []
}