{
    "crime": "999. Landroid/location/Location;getLatitude->Landroid/location/LocationManager;getLastKnownLocation",
    "permission": [],
    "api": [
        {
            "class": "Landroid/location/Location;",
            "method": "getLatitude",
            "descriptor": "()D"
        },
        {
            "class": "Landroid/location/LocationManager;",
            "method": "getLastKnownLocation",
            "descriptor": "(Ljava/lang/String;)Landroid/location/Location;"
        }
    ],
    "score": 1,
    "label": []
}